chatrepl.py
chatrepl-0.2.0a1.dist-info/licenses/LICENSE
chatrepl-0.2.0a1.dist-info/METADATA
chatrepl-0.2.0a1.dist-info/WHEEL
chatrepl-0.2.0a1.dist-info/top_level.txt
chatrepl-0.2.0a1.dist-info/RECORD
