Metadata-Version: 2.4
Name: chatrepl
Version: 0.2.0a1
Summary: A Python 2.7+ REPL for interacting with LLMs with an OpenAI Chat Completions-compatible API.
Author-email: Jifeng Wu <jifengwu2k@gmail.com>
License-Expression: MIT
Project-URL: Homepage, https://github.com/jifengwu2k/chatrepl
Project-URL: Bug Tracker, https://github.com/jifengwu2k/chatrepl/issues
Classifier: Programming Language :: Python :: 2
Classifier: Programming Language :: Python :: 3
Classifier: Operating System :: OS Independent
Requires-Python: >=2
License-File: LICENSE
Requires-Dist: chat-completions-conversation
Requires-Dist: file-to-unicode-base64-data-uri
Requires-Dist: get-unicode-multiline-input-with-editor
Requires-Dist: textcompat
Requires-Dist: typing; python_version < "3.5"
Dynamic: license-file
